LICENSE
MANIFEST.in
README.rst
setup.py
stopclock/__init__.py
stopclock.egg-info/PKG-INFO
stopclock.egg-info/SOURCES.txt
stopclock.egg-info/dependency_links.txt
stopclock.egg-info/requires.txt
stopclock.egg-info/top_level.txt