Metadata-Version: 1.1
Name: stopclock
Version: 1.0
Summary: A python package that a stopwatch/stopclock.
Home-page: https://github.com/harlowja/stopclock
Author: Joshua Harlow
Author-email: harlowja@gmail.com
License: ASL 2.0
Platform: UNKNOWN
Classifier: Development Status :: 4 - Beta
Classifier: Topic :: Utilities
Classifier: License :: OSI Approved :: Apache Software License
Classifier: Operating System :: POSIX :: Linux
Classifier: Programming Language :: Python
Classifier: Programming Language :: Python :: 2
Classifier: Programming Language :: Python :: 2.7
Classifier: Programming Language :: Python :: 3
